{
    "frames": [
        {
            "filename": "virgil_0",
            "frame": {
                "w": 64,
                "h": 64,
                "x": 0,
                "y": 0
            },
            "anchor": {
                "x": 0.5,
                "y": 0.5
            }
        },
        {
            "filename": "virgil_1",
            "frame": {
                "w": 64,
                "h": 64,
                "x": 64,
                "y": 0
            },
            "anchor": {
                "x": 0.5,
                "y": 0.5
            }
        },
        {
            "filename": "mice_incomplete_0",
            "frame": {
                "w": 64,
                "h": 64,
                "x": 0,
                "y": 64
            },
            "anchor": {
                "x": 0.5,
                "y": 0.5
            }
        },
        {
            "filename": "mice_incomplete_1",
            "frame": {
                "w": 64,
                "h": 64,
                "x": 64,
                "y": 64
            },
            "anchor": {
                "x": 0.5,
                "y": 0.5
            }
        },
        {
            "filename": "mice_complete_0",
            "frame": {
                "w": 64,
                "h": 64,
                "x": 0,
                "y": 128
            },
            "anchor": {
                "x": 0.5,
                "y": 0.5
            }
        },
        {
            "filename": "mice_complete_1",
            "frame": {
                "w": 64,
                "h": 64,
                "x": 64,
                "y": 128
            },
            "anchor": {
                "x": 0.5,
                "y": 0.5
            }
        },
        {
            "filename": "mice_kid_0",
            "frame": {
                "w": 64,
                "h": 64,
                "x": 0,
                "y": 192
            },
            "anchor": {
                "x": 0.5,
                "y": 0.5
            }
        },
        {
            "filename": "mice_kid_1",
            "frame": {
                "w": 64,
                "h": 64,
                "x": 64,
                "y": 192
            },
            "anchor": {
                "x": 0.5,
                "y": 0.5
            }
        },
        {
            "filename": "bunny_0",
            "frame": {
                "w": 64,
                "h": 64,
                "x": 0,
                "y": 256
            },
            "anchor": {
                "x": 0.5,
                "y": 0.5
            }
        },
        {
            "filename": "bunny_1",
            "frame": {
                "w": 64,
                "h": 64,
                "x": 64,
                "y": 256
            },
            "anchor": {
                "x": 0.5,
                "y": 0.5
            }
        }
    ],
    "meta": {
        "description": "Atlas generado con Atlas Packer Gamma V2",
        "web": "https://gammafp.github.io/atlas-packer-phaser/"
    }
}